packaging_tutorial/__init__.py
packaging_tutorial/main.py
packaging_tutorial_kostas885-0.1.0.dist-info/WHEEL
packaging_tutorial_kostas885-0.1.0.dist-info/METADATA
packaging_tutorial_kostas885-0.1.0.dist-info/RECORD
