Metadata-Version: 2.1
Name: packaging-tutorial-kostas885
Version: 0.1.0
Summary: 
Author: developers
Author-email: kostas@alumnireach.com
Requires-Python: >=3.9,<4.0
Classifier: Programming Language :: Python :: 3
Classifier: Programming Language :: Python :: 3.9
Classifier: Programming Language :: Python :: 3.10
Classifier: Programming Language :: Python :: 3.11
Requires-Dist: flask (>=2.2.2,<3.0.0)
